cavatina/__init__.py
cavatina/_version.py
cavatina/keyboard_layout.py
cavatina/observe.py
cavatina/rtf2xml.py
cavatina/test.py
cavatina/translator.py
Cavatina-0.1.3.dist-info/LICENSE
Cavatina-0.1.3.dist-info/METADATA
Cavatina-0.1.3.dist-info/WHEEL
Cavatina-0.1.3.dist-info/top_level.txt
Cavatina-0.1.3.dist-info/RECORD
