Metadata-Version: 2.1
Name: Cavatina
Version: 0.1.3
Summary: Musical Notation Parser for Cavatina Synthax.
Home-page: http://cavatinafont.com
Author: Alexis Luengas Zimmer
Author-email: lex@cavatinafont.com
License: LGPL
Keywords: music notation parser converter musicxml midi
Platform: UNKNOWN
Classifier: Development Status :: 4 - Beta
Classifier: Environment :: Console
Classifier: Intended Audience :: End Users/Desktop
Classifier: Intended Audience :: Developers
Classifier: License :: OSI Approved :: GNU Library or Lesser General Public License (LGPL)
Classifier: Operating System :: OS Independent
Classifier: Programming Language :: Python
Classifier: Programming Language :: Python :: 2
Classifier: Programming Language :: Python :: 2.6
Classifier: Programming Language :: Python :: 2.7
Classifier: Topic :: Multimedia :: Sound/Audio :: Conversion
Classifier: Topic :: Multimedia :: Sound/Audio :: MIDI
Classifier: Topic :: Text Processing
Requires-Dist: music21
